user_agent_th/__init__.py
user_agent_th/random_ua.json
user_agent_th/user_agent_th.py
user_agent_th-1.2.6.dist-info/METADATA
user_agent_th-1.2.6.dist-info/WHEEL
user_agent_th-1.2.6.dist-info/top_level.txt
user_agent_th-1.2.6.dist-info/RECORD
