Metadata-Version: 2.1
Name: user-agent-th
Version: 1.2.6
Summary: aaaaaaa
Home-page: 
Author: 
Author-email: 
License: MIT Licence
Platform: any
